{
"type": "FeatureCollection",
"name": "titik_sma_kota_bontang",
"crs": { "type": "name", "properties": { "name": "urn:ogc:def:crs:OGC:1.3:CRS84" } },
"features": [
{ "type": "Feature", "properties": { "id": 3, "nama": "SMA 3" }, "geometry": { "type": "Point", "coordinates": [ 117.463120962309432, 0.167960101445189 ] } },
{ "type": "Feature", "properties": { "id": 1, "nama": "SMA 1" }, "geometry": { "type": "Point", "coordinates": [ 117.498566894377873, 0.13386918328726 ] } },
{ "type": "Feature", "properties": { "id": 2, "nama": "SMA 2" }, "geometry": { "type": "Point", "coordinates": [ 117.479746490057906, 0.127979397585675 ] } },
{ "type": "Feature", "properties": { "id": 4, "nama": "SMA YPK" }, "geometry": { "type": "Point", "coordinates": [ 117.463276000102056, 0.146250543926632 ] } },
{ "type": "Feature", "properties": { "id": 5, "nama": "SMA Vidatra" }, "geometry": { "type": "Point", "coordinates": [ 117.466087244209916, 0.117979880751488 ] } },
{ "type": "Feature", "properties": { "id": 6, "nama": "SMA Bahrul Ulum" }, "geometry": { "type": "Point", "coordinates": [ 117.481823980090724, 0.136642313919071 ] } },
{ "type": "Feature", "properties": { "id": 7, "nama": "SMA Yabis" }, "geometry": { "type": "Point", "coordinates": [ 117.46462560355242, 0.137999916501132 ] } },
{ "type": "Feature", "properties": { "id": 8, "nama": "SMA Monamas" }, "geometry": { "type": "Point", "coordinates": [ 117.490054484897414, 0.131813169012689 ] } }
]
}
